msutils/VERSION
msutils/__init__.py
msutils/clonable.py
msutils/dateutil.py
msutils/httputil.py
msutils/jsonmap.py
msutils/jsonutil.py
msutils/klass.py
msutils/mathutil.py
msutils/osutil.py
msutils/pathutil.py
msutils/rangeutil.py
msutils/util.py
msutils/uuidutil.py
msutils/xmlutil.py
python_msutils-0.3.5.dist-info/LICENSE.txt
python_msutils-0.3.5.dist-info/METADATA
python_msutils-0.3.5.dist-info/WHEEL
python_msutils-0.3.5.dist-info/top_level.txt
python_msutils-0.3.5.dist-info/RECORD
